Workbook

Sheet 📋 Visão Geral
A2: 🗂️ CONTROLE DE SCRUMS — VISÃO DO GERENTE
A3: 20/03/2026 | Atualização automática — edite nas abas de cada projeto.
A5: PROJETO | B5: SCRUM MASTER | C5: GERENTE | D5: SPRINTS | E5: PIPEFY OK | F5: ATA OK | G5: STATUS REPORT | H5: TESTES APROVADOS | I5: EM TESTE | J5: ALERTA GERAL
A6: Brincar no Quintal — BNQ | B6: Vanessa | C6: João Lucas | D6: =COUNTA(BNQ!$A$9:$A1003) -> 10 | E6: =COUNTIF(BNQ!D9:D18,"✅ OK") -> 0 | F6: =COUNTIF(BNQ!E9:E18,"✅ OK") -> 0 | G6: =COUNTIF(BNQ!$F$9:$F1003,"✅ OK") -> 2 | H6: =COUNTIF(BNQ!K9:K18,"✅ Aprovado") -> 0 | I6: =COUNTIF(BNQ!K9:K18,"🔄 Em teste") -> 0 | J6: =IF(COUNTIF(BNQ!D9:D18,"🔴 Não feito")+COUNTIF(BNQ!E9:E18,"🔴 Não feito")>0,"🔴 Atenção",IF(COUNTIF(BNQ!D9:D18,"⚠️ Incompleto")+COUNTIF(BNQ!E9:E18,"⚠️ Incompleto")>0,"⚠️ Verificar","🟢 OK")) -> 🔴 Atenção
A7: Sistema Produtiva Júnior — SPJ | B7: Daniel Rannyeri | C7: João Lucas | D7: =COUNTA(SPJ!$A$9:$A1003) -> 11 | E7: =COUNTIF(SPJ!D9:D16,"✅ OK") -> 8 | F7: =COUNTIF(SPJ!E9:E16,"✅ OK") -> 8 | G7: =COUNTIF(SPJ!$F$9:$F1003,"✅ OK") -> 2 | H7: =COUNTIF(SPJ!K9:K16,"✅ Aprovado") -> 0 | I7: =COUNTIF(SPJ!K9:K16,"🔄 Em teste") -> 0 | J7: =IF(COUNTIF(SPJ!D9:D16,"🔴 Não feito")+COUNTIF(SPJ!E9:E16,"🔴 Não feito")>0,"🔴 Atenção",IF(COUNTIF(SPJ!D9:D16,"⚠️ Incompleto")+COUNTIF(SPJ!E9:E16,"⚠️ Incompleto")>0,"⚠️ Verificar","🟢 OK")) -> 🟢 OK
A8: Sistema Z2 — SZ2 | B8: João Lucas | C8: Pedro Henrique | D8: =COUNTA('EZ2'!$A$9:$A1003) -> 9 | E8: =COUNTIF('EZ2'!D9:D15,"✅ OK") -> 7 | F8: =COUNTIF('EZ2'!E9:E15,"✅ OK") -> 7 | G8: =COUNTIF('EZ2'!$F$9:$F1003,"✅ OK") -> 4 | H8: =COUNTIF('EZ2'!$K$9:$K1003,"✅ Aprovado") -> 0 | I8: =COUNTIF('EZ2'!$K$9:$K1003,"🔄 Em teste") -> 0 | J8: =IF(COUNTIF('EZ2'!D9:D15,"🔴 Não feito")+COUNTIF('EZ2'!E9:E15,"🔴 Não feito")>0,"🔴 Atenção",IF(COUNTIF('EZ2'!D9:D15,"⚠️ Incompleto")+COUNTIF('EZ2'!E9:E15,"⚠️ Incompleto")>0,"⚠️ Verificar","🟢 OK")) -> 🟢 OK
A9: Sistema AENTS — AENTS | B9: Rômulo | C9: Daniel Rannyeri | D9: =COUNTA(AENTS!$A$9:$A1003) -> 4 | E9: =COUNTIF(AENTS!$D$9:$D1003,"✅ OK") -> 4 | F9: =COUNTIF(AENTS!$E$9:$E1003,"✅ OK") -> 0 | G9: =COUNTIF(AENTS!$F$9:$F1003,"✅ OK") -> 2 | H9: =COUNTIF(AENTS!$K$9:$K1003,"✅ Aprovado") -> 0 | I9: =COUNTIF(AENTS!$K$9:$K1003,"🔄 Em teste") -> 0 | J9: =IF(COUNTIF(AENTS!$D$9:$D1003,"🔴 Não feito")+COUNTIF(AENTS!$E$9:$E1003,"🔴 Não feito")>0,"🔴 Atenção",IF(COUNTIF(AENTS!$D$9:$D1003,"⚠️ Incompleto")+COUNTIF(AENTS!$E$9:$E1003,"⚠️ Incompleto")>0,"⚠️ Verificar","🟢 OK")) -> 🔴 Atenção
A10: Sistema Rotulare — Rotulare | B10: Carlos Gabriel | C10: Pedro Henrique | D10: =COUNTA(Rotulare!$A$9:$A1003) -> 20 | E10: =COUNTIF(Rotulare!$D$9:$D1003,"✅ OK") -> 17 | F10: =COUNTIF(Rotulare!$E$9:$E1003,"✅ OK") -> 20 | G10: =COUNTIF(Rotulare!$F$9:$F1003,"✅ OK") -> 15 | H10: =COUNTIF(Rotulare!$K$9:$K1003,"✅ Aprovado") -> 0 | I10: =COUNTIF(AENTS!$K$9:$K1003,"🔄 Em teste") -> 0 | J10: =IF(COUNTIF(Rotulare!$D$9:$D1003,"🔴 Não feito")+COUNTIF(Rotulare!$E$9:$E1003,"🔴 Não feito")>0,"🔴 Atenção",IF(COUNTIF(Rotulare!$D$9:$D1003,"⚠️ Incompleto")+COUNTIF(Rotulare!$E$9:$E1003,"⚠️ Incompleto")>0,"⚠️ Verificar","🟢 OK")) -> 🔴 Atenção
A11: Sistema ODD — ODD | B11: Carlos Gabriel | C11: Daniel Rannyeri | D11: =COUNTA(ODD!$A$9:$A1003) -> 3 | E11: =COUNTIF(ODD!$D$9:$D1003,"✅ OK") -> 0 | F11: =COUNTIF(ODD!$E$9:$E1003,"✅ OK") -> 0 | G11: =COUNTIF(ODD!$F$9:$F1003,"✅ OK") -> 0 | H11: =COUNTIF(ODD!$K$9:$K1003,"✅ Aprovado") -> 0 | I11: =COUNTIF(ODD!$K$9:$K1003,"🔄 Em teste") -> 0 | J11: =IF(COUNTIF(ODD!$D$9:$D1003,"🔴 Não feito")+COUNTIF(ODD!$E$9:$E1003,"🔴 Não feito")>0,"🔴 Atenção",IF(COUNTIF(ODD!$D$9:$D1003,"⚠️ Incompleto")+COUNTIF(ODD!$E$9:$E1003,"⚠️ Incompleto")>0,"⚠️ Verificar","🟢 OK")) -> 🟢 OK
A13: 💡 COMO USAR: O gerente edita ✅ / ⚠️ / 🔴 diretamente em cada aba de projeto (colunas Pipefy e ATA). As colunas E, F, G, H e o Alerta Geral aqui na Visão Geral atualizam automaticamente. A aba 📈 Métricas também recalcula sozinha.

Sheet BNQ
A2: Brincar no Quintal — BNQ
A3: Scrum Master: Vanessa | D3: Gerente: João Lucas | I3: Atualizado: 19/05/2026 | K3: data de entrega:
A5: ="Sprints: " & COUNTA($A$9:$A1000) -> Sprints: 10 | C5: =COUNTIF($D$9:$D1000,"✅ OK")&"/" & COUNTA($D$9:$D1000) & "Pipefy ✅" -> 0/10Pipefy ✅ | E5: =COUNTIF($E$9:$E1000,"✅ OK")&"/" & COUNTA($D$9:$D1000) & "ATA ✅" -> 0/10ATA ✅ | G5: =COUNTIF($J$9:$J1000,"✅ Aprovado")&" aprovados 🧪" -> 0 aprovados 🧪 | I5: =COUNTIF($J$9:$J1000,"🔄 Em teste")&" em teste 🔄" -> 0 em teste 🔄
A7: 📋 CONTROLE DE PROCESSO | H7: 🧪 TESTES DE ENTREGA
A8: SPRINT | B8: PERÍODO | C8: ENTREGA DE VALOR | D8: PIPEFY ATUALIZADO? | E8: ATA PREENCHIDA? | F8: STATUS REPORT ENVIADO? | G8: OBS. PROCESSO (Gerente / SM) | H8: FEATURE TESTADA | I8: TESTADOR INTERNO | J8: TESTADOR EXTERNO | K8: STATUS TESTE | L8: OBS. TESTE
A9: 1 | B9: 22/04 - 05/05 | C9: Finalização do projeto | D9: 🔴 Não feito | E9: 🔴 Não feito | F9: ✅ OK | G9: Faltando apenas a homologação da conta do cliente. Pensamentos agora estão voltados para começar a produção dos aditivos
A10: 2 | B10: 06/05 - 13/05 | C10: Houve a homologação da conta do cliente | D10: 🔴 Não feito | E10: 🔴 Não feito | F10: ✅ OK | G10: Precisam marcar reunião de apresentação de mockup com o cliente para poderem prosseguir com o TAM(Aditivo do convite).
A11: 3 | B11: 13/05 - 19/05 | C11: Sem entrega de valor, pois ainda estão com o problema da homologação da conta do cliente | D11: — | E11: — | F11: — | G11: O projeto está parado, pois não teve novas demandas, já que ainda precisa da homologação da conta do cliente, além disso, o ticket que havia dado um certo trabalho expirou e agora vai começar esse processo novamente. O mockup do primeiro aditivo está pronto e o desenvolvimento está muito avançado, mas ainda precisa da apresentação e aprovação do cliente com o mockup(reunião vai ser feita essa na quinta-feira)
A12: 4 | B12: 20/05 - 26/05 | C12: --- | D12: — | E12: — | F12: — | G12: Teve reunião com o cliente para apresentação do mockup do primeiro aditivo, onde ele acabou pedindo algumas alterações e o UX do projeto já está trabalhando nessas mudanças. Quanto ao problema da homologação da conta do cliente com o banco, ainda está sendo resolvido e não teve nenhum grande avanço até então.
A13: 5 | B13: 26/05 - 03/06 | C13: --- | D13: — | E13: — | F13: — | G13: As alterações do mockup estão prontas, faltando apenas apresentar para o cliente em uma reunião que ainda está para ser marcada. Sobre a homologação da conta, ainda está tendo problemas (um dia sai). Está para ser marcada uma reunião com a equipe para fazer alguns alinhamentos, pois fazem 2 semanas que eles não têm reuniões
A14: 6 | B14: 04/06 - 08/07 | D14: — | E14: — | F14: — | G14: Tentando marcar reunião com o cliente e será marcado uma reunião com os devs backends do projeto para tentar resolver o problema do pagseguro e para fazer a integração do Ryan
A15: 7 | B15: 09/07 - 15/07 | D15: — | E15: — | F15: — | G15: Reunião com o cliente ainda no aguardo para acontecer. Sobre a homologação da conta do cliente, começaram os avanços e talvez esteja perto desse problema ser resolvido
A16: 8 | B16: 16/07 - 22/07 | D16: — | E16: — | F16: — | G16: A reunião com o cliente ainda não conseguiu ser marcada. Além disso houve a troca de PO no projeto e a homologação da conta do cliente continua avançando
A17: 9 | B17: 46225 | D17: — | E17: — | F17: — | G17: A homologação da conta do cliente ainda não foi concluída, é um prcoesso que leva tempo e Gabriel encontrou alguns empecilhos. Vai ser feita uma reunião com a equipe para alinhar com eles tudo que vem acontecendo no projeto. Nessa reunião há o objetivo de fazer uma devida introdução de Guilherme ao projeto e passar pra ele a demanda de marcar a reunião com o cliente
A18: 10 | B18: 28/08 - Atual | D18: — | E18: — | F18: — | G18: Tiveram reunião com cliente sexta-feira(28/08) para aprensetação do mockup, onde o cliente pediu algumas alterações que já foram corrigidas e estão prontas para apresentar. A equipe vai passar por uma nova troca de PO, mas enquanto isso Vanessa está assumindo essa comunicação com o cliente e quer adiantar o TAM, pois quer fazer a última reunião de apresentação de mockup. Sobre a homologação da conta do cliente, basicamente teve que reiniciar o processo, pois durante a reunião criaram um card junto com o cliente e essa semana Gabriel e Roni, em uma nova reunião para resolver esse problema, perceberam que um e-email que foi enviado para eles acabou caindo no spam de ambos.

Sheet SPJ
A2: Sistema Produtiva Júnior — SPJ
A3: Scrum Master: Daniel Rannyeri | D3: Gerente: João Lucas | I3: Atualizado: 17/05/2026
A5: ="Sprints: " & COUNTA($A$9:$A998) -> Sprints: 11 | C5: =COUNTIF($D$9:$D998,"✅ OK")&"/" & COUNTA($D$9:$D998) & "Pipefy ✅" -> 11/11Pipefy ✅ | E5: =COUNTIF($E$9:$E998,"✅ OK")&"/" & COUNTA($D$9:$D998) & "ATA ✅" -> 9/11ATA ✅ | H5: =COUNTIF($K$9:$K998,"✅ Aprovado")&" aprovados 🧪" -> 0 aprovados 🧪 | J5: =COUNTIF($K$9:$K998,"🔄 Em teste")&" em teste 🔄" -> 0 em teste 🔄
A7: 📋 CONTROLE DE PROCESSO | H7: 🧪 TESTES DE ENTREGA
A8: SPRINT | B8: PERÍODO | C8: ENTREGA DE VALOR | D8: PIPEFY ATUALIZADO? | E8: ATA PREENCHIDA? | F8: STATUS REPORT ENVIADO? | G8: OBS. PROCESSO (Gerente / SM) | H8: FEATURE TESTADA | I8: TESTADOR INTERNO | J8: TESTADOR EXTERNO | K8: STATUS TESTE | L8: OBS. TESTE
A9: 1 | B9: 24/05 - 07/05 | C9: Correção de bugs, ajuste de botões e criação do mockup da tela de cadastro | D9: ✅ OK | E9: ✅ OK | F9: 🔴 Não feito | G9: Tempo turbulento por causa do Portto, as tarefas foram de fazer ajustes de código, reponsividade, botões e refatoração de código no back
A10: 2 | B10: 08/05 - 14/05 | C10: Função de cadastramento dos estudantes | D10: ✅ OK | E10: ✅ OK | F10: ⚠️ Incompleto | G10: Front está responsável por refatorar códigos de partes diferentes do projeto. Back também fico responsável por refatorar código. O UX do projeto está de folga
A11: 3 | B11: 14/05 - 21/05 | C11: Querem marcar reunião para apresentar uma função de cadastro do estundante, mas essa funcionalidade ainda está um pouco confusa, então precisam conversar com o pessoal da PJ para entender melhor | D11: ✅ OK | E11: ✅ OK | F11: ✅ OK | G11: Front fez algumas refatorações e criou uma nova branch, para essa semana ficou responsável por realizar mais refatorações, dessa vez no CSS. Back refatorou muitas linhas de código e para essa semana ficou responsável por criar um modelo de faturamento(pedido do cliente)
A12: 4 | B12: 21/05 - 28/05 | C12: Sem entrega de valor já que a PJ não está colaborando | D12: ✅ OK | E12: ✅ OK | F12: ✅ OK | G12: Front: Corrigir erro na responsividade do ícone de filtro; Corrigir erro na responsividade ao clicar no Botão Perfil; Refatorar os arquivos CSS da página de Estudantes. Back: Adicionar o campo de faturamento e deixar editável; Ajustar o campo "Captar em" trocando para "Faturamento" e ajustando o campo para corresponder ao faturamento; Atualizar o README.md no repositório do Github. Continuam na batalha para tentar marcar a bendita reunião com o pessoal da PJ
A13: 5 | B13: 28/05 - 04/06 | D13: ✅ OK | E13: ✅ OK | G13: Ainda não conseguiram marcar a reunião com a PJ, talvez façam um documento para apresentar a proposta ao pessoal da PJ, já que não conseguem uma reunião. O front ficou responsável por corrigir alguns erros de responsividade e refatorar arquivos de CSS, além de estar ajustando algumas coisas na tela de cadastro. O back, mesmo sem muitas informações, criou algumas tarefas para a parte de faturamento e fez o campo de faturamento, deixou ele editável e continua mexendo
A14: 6 | B14: 04/06 - 11/06 | D14: ✅ OK | E14: ✅ OK | G14: Cliente continua sem marcar reuniões e dificultando os avanços do projeto. O front está trabalhando em refatoração de código e correção de bugs. O back ficou sem demandas, pois precisa das informações que a cliente não está fornecendo
A15: 7 | B15: 11/06 - 25/06 | D15: ✅ OK | E15: ✅ OK | G15: O projeto está parado, pois passamos pela semana de avaliação dos trainees, além de estarem na busca pela bendita reunião com a cliente, que continua adiando o momento
A16: 8 | B16: 26/06 - 08/07 | D16: ✅ OK | E16: ✅ OK | G16: Os clientes não estão respondendo, então o projeto vai seguir com o que a equipe considera ser o certo até que se tenha uma resposta da PJ
A17: 9 | B17: 09/07 - 16/07 | D17: ✅ OK | E17: ✅ OK | G17: JV foi introduzido ao projeto e pegou pequenas demandas para essa semana (ver e entender o código), Rafa dando o suporte como padrinha. Rafa e PH estão ajudando a criar os novos backlogs para o prosseguimento do projeto. Além disso, já está sendo pensado em montar uma equipe de testes.
A18: 10 | B18: 17/07 - 24/04 | D18: ✅ OK | E18: — | G18: Durante o intensivão foram feitos testes no sistema, agora os devs deram continuidade e criaram novos testes para serem feitos. Para ajudar, a equipe tá com acesso ao Claude da EJECT para conseguir acelerar o processo
A19: 11 | B19: 31/08 - atual | D19: ✅ OK | E19: — | G19: Colocaram Tainá e Gabriel Augusto para testarem o sistema, mas ainda não começaram, pois está sendo organizada a planilha de testes para poder organizar o que será feito. O projeto está próximo de ser entregue, conforme o que tá sendo pensado pela equipe (já que os clientes não deram mais nenhuma notícia). As tarefas atualmente estão mais focadas do back, faltando basicamanete a parte de cadastro de empresários.

Sheet EZ2
A2: Sistema EZ2 — EZ2
A3: Scrum Master: João Lucas | D3: Gerente: Pedro Henrique | I3: Atualizado: 04/09/2026
A5: ="Sprints: " & COUNTA($A$9:$A1000) -> Sprints: 9 | C5: =COUNTIF($D$9:$D1000,"✅ OK")&"/" & COUNTA($D$9:$D1000) & "Pipefy ✅" -> 9/9Pipefy ✅ | E5: =COUNTIF($E$9:$E1000,"✅ OK")&"/" & COUNTA($D$9:$D1000) & "ATA ✅" -> 9/9ATA ✅ | H5: =COUNTIF($K$9:$K1000,"✅ Aprovado")&" aprovados 🧪" -> 0 aprovados 🧪 | J5: =COUNTIF($K$9:$K1000,"🔄 Em teste")&" em teste 🔄" -> 0 em teste 🔄
A7: 📋 CONTROLE DE PROCESSO | H7: 🧪 TESTES DE ENTREGA
A8: SPRINT | B8: PERÍODO | C8: ENTREGA DE VALOR | D8: PIPEFY ATUALIZADO? | E8: ATA PREENCHIDA? | F8: STATUS REPORT ENVIADO? | G8: OBS. PROCESSO (Gerente / SM) | H8: FEATURE TESTADA | I8: TESTADOR INTERNO | J8: TESTADOR EXTERNO | K8: STATUS TESTE | L8: OBS. TESTE
A9: Kick off + Sprint 1 | B9: 22/05 - 05/06 | C9: Planejamento e classificação de complexidade dos componentes da tela inicial, bloco de serviços e formulário de conversão de visitas. | D9: ✅ OK | E9: ✅ OK | F9: — | G9: A reunião teve como objetivo classificar e pontuar a complexidade dos componentes que serão desenvolvidos, foi utilizada a metodologia de poker planning. Além disso foram delegadas as atividades, porém, os desenvolvedores do frontend não puderam concluir devido a semanas atípicas.
A10: Sprint 2 | B10: 06/06 - 12/06 | C10: Analise e classificação da dificuldade da tela "Quem Somos" atraves do método "Poker Planning". Além disso, também foram criados os endpoints dos indicadores. | D10: ✅ OK | E10: ✅ OK | F10: ✅ OK | G10: Durante a coleta das atividades foi relatado que tanto um dos fronts quanto o UX/UI não conseguiram realizar as entregas previstas. Porém, ambas as situações foram relatadas com previedade ao Scrum Master.
A11: Sprint 3 | B11: 13/06 - 27/06 | C11: Entrega dos componentes de Footer e Navbar e entrega parcial dos endpoints de depoimentos | D11: ✅ OK | E11: ✅ OK | F11: ✅ OK | G11: Devido a ida de alguns membros ao Destine'26 a próxima sprint terá duas semanas de duração.
A12: Sprint 4 | B12: 28/06 - 13/07 | C12: Entrega da seção de serviços na tela inicial com responsividade, inicio da criação do banner da tela inicial e entrega parcial dos endpoints de depoimentos e dinamização dos cards de serviço. | D12: ✅ OK | E12: ✅ OK | F12: ✅ OK | G12: Durante essas duas semanas houveram alguns imprevistos como o computador de Levy, frontend, quebrar, a participação de Vanessa, frontend, no Destine e também a mudança de país de Gabriel, backend. Porém, as atividades estão se normalizando na medida do possível.
A13: Sprint 5 | B13: 14/07 - 20/07 | C13: Todas as atividades catalogadas para serem realizadas pelo backend foram finalizadas. | D13: ✅ OK | E13: ✅ OK | F13: ✅ OK | G13: O desenvolvedor Gabriel Nascimento foi inserido na equipe para auxiliar com possíveis ajustes futuramente e para se integrar ao ciclo de desenvolvimento de um projeto, porém, o backend está com maior parte das suas atividades finalizada. Ambos os desenvolvedores do fronend estão finalizando suas respectivas atividades e devem realizar as entregas delas na seguinte sprint.
A14: Sprint 6 | B14: 21/07 - 27;07 | C14: Entrega do componente de banner que será utilizado em 4 telas. Entrega dos componentes de indicadores, cards de serviço e formulário (apenas versão desktop) da tela inicial. | D14: ✅ OK | E14: ✅ OK | F14: — | G14: O desenvolvedor Gabriel Teixeira promoveu uma capacitação de Docker para o restante da equipe a fim de tornar o trabalho dos devs de front-end menos complicado no que diz respeito a configuração de ambiente de testes.
A15: Sprint 7 | B15: 28/07 - 03/08 | C15: Entrega do carrossel do baner da tela inicial e das seções de "Nossa História", "Misão", "Visão" e "Valores". Desenvolvimento da versão mobile do formulário da tela inicial e do formulário de orçamento da tela de orçamento. | D15: ✅ OK | E15: ✅ OK | F15: — | G15: Foi decidio que a próxima sprint durará até o dia 15/08. Além disso, foin acordado será realizada a tentativa de marcação de uma reunião com a cliente para a próxima semana, ou seja, dentro da semana que vai de 10/08 a 14/08.
A16: Sprint 8 | B16: 04/08 - 15/08 | C16: Entrega do carrossel dos parceiros na tela "Quem Somos" | D16: ✅ OK | E16: ✅ OK | F16: — | G16: A reunião com a cliente ainda não pôde ser marcada, porém a expectativa é que seja realizada durante a sprint atual. Foi levantada a possibilidade que seja realizada a noite ou durante o fim de semana, porém precisaremos confirmar com a cliente se realmetne é viável.
A17: Sprint 9 | B17: 16/08 - 22/08 | C17: Entrega de elemento de depoimento do carrossel da tela inicial e correção de problemas com a api que impossibilitavam a integração com o frontend. | D17: ✅ OK | E17: ✅ OK | F17: — | G17: Durante essa semana ocorreu a reunião com os clientes, porém, a representante da EZ2 que apareceu não foi uma das que tratamos normalmente, portanto, ela não pôde fazer uma análise como as outras fariam. Entretanto, a reunião teve seu objetivo pontual alcançado, isto é, realizar a demonstração dos avanços para a representante da empresa. Será marcada outra reunião para daqui duas sprints e a ideia é que seja com as stakeholders que tratamos no "dia a dia".

Sheet Rotulare
A2: Rotulare
A3: Scrum Master: Carlos Gabriel | D3: Gerente: Pedro Henrique | I3: Atualizado: 04/09/2026
A5: ="Sprints: " & COUNTA($A$9:$A1022) -> Sprints: 20 | C5: =COUNTIF($D$9:$D1022,"✅ OK")&"/" & COUNTA($D$9:$D1022) & "Pipefy ✅" -> 17/20Pipefy ✅ | E5: =COUNTIF($E$9:$E1022,"✅ OK")&"/" & COUNTA($D$9:$D1022) & "ATA ✅" -> 20/20ATA ✅ | H5: =COUNTIF($K$9:$K1022,"✅ Aprovado")&" aprovados 🧪" -> 0 aprovados 🧪 | J5: =COUNTIF($K$9:$K1022,"🔄 Em teste")&" em teste 🔄" -> 0 em teste 🔄
A7: 📋 CONTROLE DE PROCESSO | H7: 🧪 TESTES DE ENTREGA
A8: SPRINT | B8: PERÍODO | C8: ENTREGA DE VALOR | D8: PIPEFY ATUALIZADO? | E8: ATA PREENCHIDA? | F8: STATUS REPORT ENVIADO? | G8: OBS. PROCESSO (Gerente / SM) | H8: FEATURE TESTADA | I8: TESTADOR INTERNO | J8: TESTADOR EXTERNO | K8: STATUS TESTE | L8: OBS. TESTE
A9: Sprint "1" | B9: 13/04 - 20/04 | C9: Módulos de usuários, fornecedores e custos | D9: ✅ OK | E9: ✅ OK | F9: ✅ OK | G9: Os módulos de usuários e custos passarão por correçoes, mas o módulo de fornecedores não teve objeções. Além disso, o projeto atualmente não possui um Scrum Master (o diretor de projetos está a frente), portanto não possui ata de sprint. Houve reunião com a cliente nessa semana. | L9: Os testes não estão estruturados, esse ponto será corrigido para a próxima sprint
A10: Sprint 2 | B10: 20/04 - 28/04 | C10: Correções no módulo de fornecedores e tipos de usuáro com permissões ajustadas. | D10: ✅ OK | E10: ✅ OK | F10: ✅ OK | G10: A sprint teve que ter um dia a mais devido a reunião de alinhamento do apadrinhamento dos trainees. O primeiro status report foi enviado. O projeto agora possui ata de sprint review e o SM é Carlos Gabriel, diretor de projetos. | L10: Seguimos com os problemas dos testes, porém estamos tentando o sistema conforme vamos corrigindo.
A11: Sprint 3 | B11: 29/04 - 04/05 | C11: Correções pendentes da última sprint, pois após a validação com a cliente ela pontuou pontos de melhoria. | D11: ⚠️ Incompleto | E11: ✅ OK | F11: 🔴 Não feito | G11: Nos dias 02/05 e 03/05 ocorreu o Portto'26, evento do MEJ em Mossoró e 3 dos 4 membros do projeto estavam presentes, portanto foi decido que seria uma semana mais tranquila visto que a disponibilidade seria baixa. | L11: Não foram realizados testes
A12: Sprint 4 | B12: 05/05 - 12/05 | C12: Validação dos esboços da tela de controle de estoque com a cliente. | D12: ✅ OK | E12: ✅ OK | F12: ✅ OK | G12: A reunião com a cliente aconteceu no dia 09/05 e contou coma presença do P.O e do SM. A cliente validou e corrigiu os esboços, porém ainda será necessário apresentar outra versão para bater o martelo.
A13: Sprint 5 | B13: 13/05 - 18/05 | C13: Correções nos componentes de menu hambuguer e footer, além de correções pontuais na botão de pesquisa no módulo de controle de estoque. Além disso, foi corrigido o esboço da tela principal do módulo de controle de estoque. | D13: ✅ OK | E13: ✅ OK | F13: ✅ OK | G13: O esboço criado nessa sprint será validado com a cliente. A equipe está apenas com um desenvolvedor frontend ativo e um backend, sendo também o Scrum Master do projeto.
A14: Sprint 6 | B14: 19/05 - 25/05 | C14: Validação do esboço final que será utilizado na tela de controle de estoque. Correções em bugs nos cards de ficha técnica e estruturação das permissões do sistemas entre tipos de usuários. | D14: ✅ OK | E14: ✅ OK | F14: ✅ OK | G14: Algumas atividades dessa semana tiveram desdobramentos, portanto foram passados seus extras para a sprint atual, mas algumas causas são o código legado do projeto.
A15: Sprint 7 | B15: 26/05 - 01/06 | C15: Reestruturação dos cards de ficha técnica a fim de dar melhor visibilidade para a imagem do card e correção dos ajustes de permissões do usuário cozinha. Além de correções na navbar e no footer. | D15: ✅ OK | E15: ✅ OK | F15: ✅ OK | G15: Foi notada que a remodelagem do banco de dados terá de ser estudada e subdivididas em tarefas menores, visto que envolve um escopo bem maior do que o previsto. Outro ponto de destaque é que foi identificado que não há uma tela especifica para editar pedido, portanto é mais uima atividade que será planejada e subdividada.
A16: Sprint 8 | B16: 02/06 - 08/06 | C16: --- | D16: ✅ OK | E16: ✅ OK | F16: — | G16: As atividades da sprint não puderam ser realizadas devido a sobrecarga dos membros com outras atividades, tanto da faculdade, quanto pessoais. A cliente foi informada do ocorrido, porém não foi confeccionado Status Report porque não havia o que reportar, porém a cliente foi informada do ocorrido.
A17: Sprint 9 | B17: 09/06 - 15/06 | C17: Parte estática da tela de controle de estoque e criação da lógica e telas de edição de pedido. | D17: ✅ OK | E17: ✅ OK | F17: ✅ OK | G17: Foi marcada a reunião com a cliente para a validação do desenvolvimento do novo design da tela de controle de estoque. A reunião será 20/06 as 15h30.
A18: Sprint 10 | B18: 16/06 - 22/06 | C18: Reunião com a cliente para mostrar o novo design da tela de controle de estoque e Inicio da dinamização da nova tela de controle de estoque. | D18: ✅ OK | E18: ✅ OK | F18: ✅ OK | G18: A reunião ocorreu no dia 20/06 pela manhã e correu como prevista, nela foi apresentada a tela de controle de estoque com o novo design e também foi alinhado com a cliente que um novo prazo de entrega realista seria planejado.
A19: Sprint 11 | B19: 23/06 - 29/06 | C19: Não houve nenhuma | D19: 🔴 Não feito | E19: ✅ OK | F19: 🔴 Não feito | G19: Essa semana foi marcada pelo ingresso dos novos membros, a semana do Destine'26, ou seja, semana de 3 dias úteis e a penultima semana do semestre letivo, portanto, não foi possível realizar atividades na sprint.
A20: Sprint 12 | B20: 30/06 - 06/07 | C20: Dinamização da tela de controle de estoque e ajuste na reponsividade, ajustes na responsividade da tela de insumos alimentares e correção no espaçamento do formulário de cadastro da tela de cadastro de usuário. Ajustes na versão mobile dos módulos de preço de venda, insumos alimentares e ficha ténica. | D20: ✅ OK | E20: ✅ OK | F20: ✅ OK | G20: Os novos membros receberam suas primeiras atividades e iniciaram o processo de habituar-se ao sistema. Levy, desenvolvedor front-end, teve seu notebook danificado e está buscando meios de viabilizar o desenvolvimento. Além disso, a desenvolvedora front-end Thamyres também está com problemas pessoais e precisará se afastar por um tempo.
A21: Sprint 13 | B21: 07/07 - 13/07 | C21: A atividade de adição de campo extra no alergênico específico no módulo de Ficha Técnica foi a única realizada em sua completude. | D21: ✅ OK | E21: ✅ OK | F21: ✅ OK | G21: Levy segue com problemas técnicos e foi impossibilitado de dar seguimento as suas atividades e Thamyres segue afastada por motivos pessoais, portanto não há avanços significativos no frontend. Porém, Emanuel e José Fernandes tiveram avanços em suas atividades. Além disso, a nova P.O do projeto, Rebecca, foi introduzida a equipe e será acompanhada pelo gerente, Pedro Henrique, durante o período de adaptação.
A22: Sprint 14 | B22: 14/07 - 20/07 | C22: Foi finalizada a atividade de adicionar um alergenico a lista de escolhas no módulo de Ficha Técnica e foi conduzido um estudo sobre valores incosistentes no módulo de Preço de Venda. | D22: ✅ OK | E22: ✅ OK | F22: ✅ OK | G22: Houve uma reunião com a cliente no sábado, dia 18/07, e foram alinhadas informações sobre os módulos de Dashboard e Pedidos. A desenvolvedora front-end Thamyres retornou a equipe e o notebook do desenvolvedor front-end Levy está cotado para chegar no dia 21/07, portanto é esperado que o front-end do projeto volte a seu fluxo comum.
A23: Sprint 15 | B23: 21/07 - 27/07 | C23: Foi entregue a correção dos links da página de login na página institucional, o ajuste no botão que leva a página de pagamento e a restrição visual do sistema quando o usuário estiver inadimplente. | D23: ✅ OK | E23: ✅ OK | F23: ✅ OK | G23: A coleta de atividades da sprint foi realizada durante o intensivão, além disso, também foi realizada uma rodada de testes de onde surgiram diversos cards de atividades que irão ser corriidos nas próximas sprints.
... A28: Sprint 20 | B28: 25/08 - 01/09 | C28: No frontend foi realizar a correção da tela de "Detelhes da mesa" que estava com incosistências na estilização, foi realizada também a correção do vazamento de texto dos cards de mesa ativos, foi adicionado a primeira versão de mensagem de confirmação na criação de pedidos e mensagens de restrições quando um pedido é criado indevidamente. No backend forám corrigidas incosistências de descosto de valores no estoque e adição de lógica para utilização de mensagens de confirmação de deleção ou criação. | D28: ✅ OK | E28: ✅ OK | F28: — | G28: Atualmente o projeto está passando pelo período de transição de Scrum Master onde Carlos Gabriel, atual diretor de projetos, está saindo do cargo e Pedro Henrique, atual gerente, porém na última semana do exercício da função, está assumindo o cargo. As atividades da próxima sprint serão concentradas em planejamento, adaptação e definição de cronograma e próximos passos. Além disso, no dia 30/08, as 10 da manhã, ocorreu a reunião com a cliente do projeto. A reunião correu conforme o esperado, porém, a cliente solicitou um planejamento e cronograma sobre as próximas entregas e sobre a data de finalização do projeto.

Sheet AENTS
A2: Sistema AENTS — AENTS
A3: Scrum Master: Rômulo | D3: Gerente: Danibala | I3: Atualizado: 22/04/2026
A5: ="Sprints: " & COUNTA($A$9:$A1000) -> Sprints: 4 | C5: =COUNTIF($D$9:$D1000,"✅ OK")&"/" & COUNTA($D$9:$D1000) & "Pipefy ✅" -> 4/4Pipefy ✅ | E5: =COUNTIF($E$9:$E1000,"✅ OK")&"/" & COUNTA($D$9:$D1000) & "ATA ✅" -> 0/4ATA ✅ | H5: =COUNTIF($K$9:$K1000,"✅ Aprovado")&" aprovados 🧪" -> 0 aprovados 🧪 | J5: =COUNTIF($K$9:$K1000,"🔄 Em teste")&" em teste 🔄" -> 0 em teste 🔄
A7: 📋 CONTROLE DE PROCESSO | H7: 🧪 TESTES DE ENTREGA
A8: SPRINT | B8: PERÍODO | C8: ENTREGA DE VALOR | D8: PIPEFY ATUALIZADO? | E8: ATA PREENCHIDA? | F8: STATUS REPORT ENVIADO? | G8: OBS. PROCESSO (Gerente / SM) | H8: FEATURE TESTADA | I8: TESTADOR INTERNO | J8: TESTADOR EXTERNO | K8: STATUS TESTE | L8: OBS. TESTE
A9: Sprint 1 | B9: 17/04–24/04 | D9: ✅ OK | E9: 🔴 Não feito | F9: ✅ OK | G9: Não irá conseguir entregar o Projeto dia 25, pois vão ter mais telas adicionais. Planejamento da finalização do Projeto está em torno de 3 semanas a 1 mês, com testes. O Front está desenvolvendo a tela de administrador e, logo em seguida, irá para telas adicionais. O Back está finalizado até então.
A10: Sprint "2" | B10: 46154 | D10: ✅ OK | E10: 🔴 Não feito | F10: ✅ OK | G10: Se reuniu com o cliente para entender sobre as funcionalidades de Renovação de Matrícula e a Cobrança de Mensalidade com Atraso. Foi uma reunião de bastante dúvidas, por que quanto mais eles falavam, mais dúvidas surgiam. Fizeram mais uma Sprint extra nessa semana apenas com os backs, pois vai precisar refatorar algumas coisas, como: pagamento, quantidade de semestres para cada instituição (que isso engloba também a parte de pagamento). Back vai fazer uma quantidade boa de ajustes na semana e o Front continuar ajustes nos cadastros e desenvolvimento normal.
A11: Sprint 3 | B11: 12/05-15/05 | D11: ✅ OK | E11: 🔴 Não feito | F11: 🔴 Não feito | G11: Front continua com o desenvolvimento da tela do Painel Administrativo. Back está com atividades dos ajustes que vão ser precisos no sistema de pagamento, que é gerar links de pagamento pra todos os estudantes no dia 1 até dia 15, e outros do dia 16 até o dia 1 com 1% de taxa pra quem não pagou o primeiro.
A12: Sprint 3 | B12: 15/05 - 22/05 | D12: ✅ OK | E12: 🔴 Não feito | F12: 🔴 Não feito | G12: Front continua com o desenvolvimento da tela do Painel Administrativo. Back está com atividades dos ajustes que vão ser precisos no sistema de pagamento, que é gerar links de pagamento pra todos os estudantes no dia 1 até dia 15, e outros do dia 16 até o dia 1 com 1% de taxa pra quem não pagou o primeiro.

Sheet ODD
A2: ODD
A3: Scrum Master: Carlos Gabriel | D3: Gerente: Daniel Rannyeri | I3: Atualizado: 20/03/2026
A5: ="Sprints: " & COUNTA($A$9:$A1000) -> Sprints: 3 | C5: =COUNTIF($D$9:$D1000,"✅ OK")&"/" & COUNTA($D$9:$D1000) & "Pipefy ✅" -> 0/3Pipefy ✅ | E5: =COUNTIF($E$9:$E1000,"✅ OK")&"/" & COUNTA($D$9:$D1000) & "ATA ✅" -> 0/3ATA ✅ | H5: =COUNTIF($K$9:$K1000,"✅ Aprovado")&" aprovados 🧪" -> 0 aprovados 🧪 | J5: =COUNTIF($K$9:$K1000,"🔄 Em teste")&" em teste 🔄" -> 0 em teste 🔄
A7: 📋 CONTROLE DE PROCESSO | H7: 🧪 TESTES DE ENTREGA
A8: SPRINT | B8: PERÍODO | C8: ENTREGA DE VALOR | D8: PIPEFY ATUALIZADO? | E8: ATA PREENCHIDA? | F8: STATUS REPORT ENVIADO? | G8: OBS. PROCESSO (Gerente / SM) | H8: FEATURE TESTADA | I8: TESTADOR INTERNO | J8: TESTADOR EXTERNO | K8: STATUS TESTE | L8: OBS. TESTE
A9: Sprint "1" | B9: 46153 | C9: Finalização do Manual do sistema | D9: — | E9: — | G9: Semana usada para documentar o código no manual, estruturando-o. Alguns ajustes em relação ao que tange a robutez do tratamento de erros. Carlos Gabriel está tentando realizar o deploy do sistema, mas está com alguns problemas, pois o deploy só está funcionando no domínio da UFRN. Já está com as credencias do Professor para Hospedar.
A10: Sprint 2 | B10: 11/05 -15/05 | D10: — | E10: — | G10: Esperando o Deploy que será realizado por Carlos Gabriel e testes no sistema realizado por Daniel Rannyeri para correção de possíveis erros.
A11: Sprint 3 | B11: 15/05 - 21/05 | D11: — | E11: — | G11: Feito o deploy e que o TEP já está finalizado. Esperando outra reunião com cliente do dia 03/06.

Sheet 📈 Métricas
A2: 📈 MÉTRICAS POR SQUAD
A4: PROJETO | B4: SPRINTS | C4: PIPEFY OK | D4: PIPEFY INCOMPL. | E4: PIPEFY NÃO FEITO | F4: ATA OK | G4: ATA INCOMPL. | H4: ATA NÃO FEITA
A5: Brincar no Quintal — BNQ | B5: =COUNTA(BNQ!$A$9:$A1007) -> 10 | C5: =COUNTIF(BNQ!$D$9:$D1007,"✅ OK") -> 0 | D5: =COUNTIF(BNQ!$D$9:$D1007,"⚠️ Incompleto") -> 0 | E5: =COUNTIF(BNQ!$D$9:$D1007,"🔴 Não feito") -> 2 | F5: =COUNTIF(BNQ!$E$9:$E1007,"✅ OK") -> 0 | G5: =COUNTIF(BNQ!$E$9:$E1007,"⚠️ Incompleto") -> 0 | H5: =COUNTIF(BNQ!$E$9:$E1007,"🔴 Não feito") -> 2
A6: Sistema Produtiva Júnior — SPJ | B6: =COUNTA(SPJ!$A$9:$A1007) -> 11 | C6: =COUNTIF(SPJ!$D$9:$D1007,"✅ OK") -> 11 | D6: =COUNTIF(SPJ!$D$9:$D1007,"⚠️ Incompleto") -> 0 | E6: =COUNTIF(SPJ!$D$9:$D1007,"🔴 Não feito") -> 0 | F6: =COUNTIF(SPJ!$E$9:$E1007,"✅ OK") -> 9 | G6: =COUNTIF(SPJ!$E$9:$E1007,"⚠️ Incompleto") -> 0 | H6: =COUNTIF(SPJ!$E$9:$E1007,"🔴 Não feito") -> 0
A7: Sistema Z2 — SZ2 | B7: =COUNTA('EZ2'!$A$9:$A1007) -> 9 | C7: =COUNTIF('EZ2'!$D$9:$D1007,"✅ OK") -> 9 | D7: =COUNTIF('EZ2'!$D$9:$D1007,"⚠️ Incompleto") -> 0 | E7: =COUNTIF('EZ2'!$D$9:$D1007,"🔴 Não feito") -> 0 | F7: =COUNTIF('EZ2'!$E$9:$E1007,"✅ OK") -> 9 | G7: =COUNTIF('EZ2'!$E$9:$E1007,"⚠️ Incompleto") -> 0 | H7: =COUNTIF('EZ2'!$E$9:$E1007,"🔴 Não feito") -> 0
A8: Sistema AENTS — AENTS | B8: =COUNTA(AENTS!$A$9:$A1007) -> 4 | C8: =COUNTIF(AENTS!$D$9:$D1007,"✅ OK") -> 4 | D8: =COUNTIF(AENTS!$D$9:$D1007,"⚠️ Incompleto") -> 0 | E8: =COUNTIF(AENTS!$D$9:$D1007,"🔴 Não feito") -> 0 | F8: =COUNTIF(AENTS!$E$9:$E1007,"✅ OK") -> 0 | G8: =COUNTIF(AENTS!$E$9:$E1007,"⚠️ Incompleto") -> 0 | H8: =COUNTIF(AENTS!$E$9:$E1007,"🔴 Não feito") -> 4
A9: Sistema Rotulare — Rotulare | B9: =COUNTA(Rotulare!$A$9:$A1007) -> 20 | C9: =COUNTIF(Rotulare!$D$9:$D1007,"✅ OK") -> 17 | D9: =COUNTIF(Rotulare!$D$9:$D1007,"⚠️ Incompleto") -> 2 | E9: =COUNTIF(Rotulare!$D$9:$D1007,"🔴 Não feito") -> 1 | F9: =COUNTIF(Rotulare!$E$9:$E1007,"✅ OK") -> 20 | G9: =COUNTIF(Rotulare!$E$9:$E1007,"⚠️ Incompleto") -> 0 | H9: =COUNTIF(Rotulare!$E$9:$E1007,"🔴 Não feito") -> 0
A10: Sistema ODD — ODD | B10: =COUNTA(ODD!$A$9:$A1007) -> 3 | C10: =COUNTIF(ODD!$D$9:$D1007,"✅ OK") -> 0 | D10: =COUNTIF(ODD!$D$9:$D1007,"⚠️ Incompleto") -> 0 | E10: =COUNTIF(ODD!$D$9:$D1007,"🔴 Não feito") -> 0 | F10: =COUNTIF(ODD!$E$9:$E1007,"✅ OK") -> 0 | G10: =COUNTIF(ODD!$E$9:$E1007,"⚠️ Incompleto") -> 0 | H10: =COUNTIF(ODD!$E$9:$E1007,"🔴 Não feito") -> 0
A11: TOTAL | B11: =SUM(B5:B10) -> 57 | C11: =SUM(C5:C10) -> 41 | D11: =SUM(D5:D10) -> 2 | E11: =SUM(E5:E10) -> 3 | F11: =SUM(F5:F10) -> 38 | G11: =SUM(G5:G10) -> 0 | H11: =SUM(H5:H10) -> 6
A13: 📊 TAXA DE CONFORMIDADE POR SQUAD
A14: PROJETO | B14: PIPEFY OK % | C14: ATA OK % | D14: TESTES APROVADOS | E14: EM TESTE | F14: REPROVADOS | G14: ⚠️ ALERTAS PIPEFY+ATA | H14: STATUS GERAL
A15: Brincar no Quintal — BNQ | B15: =IFERROR(COUNTIF(BNQ!$D$9:$D1007,"✅ OK")/MAX(COUNTA(BNQ!$D$9:$D1007),1),0) -> 0 | C15: =IFERROR(COUNTIF(BNQ!$E$9:$E1007,"✅ OK")/MAX(COUNTA(BNQ!$E$9:$E1007),1),0) -> 0 | D15: =COUNTIF(BNQ!$K$9:$K1007,"✅ Aprovado") -> 0 | E15: =COUNTIF(BNQ!$K$9:$K1007,"🔄 Em teste") -> 0 | F15: =COUNTIF(BNQ!$K$9:$K1007,"🔴 Reprovado") -> 0 | G15: =COUNTIF(BNQ!$D$9:$D1007,"🔴 Não feito")+COUNTIF(BNQ!$D$9:$D1007,"⚠️ Incompleto")+COUNTIF(BNQ!$E$9:$E1007,"🔴 Não feito")+COUNTIF(BNQ!$E$9:$E1007,"⚠️ Incompleto") -> 4 | H15: =IF(COUNTIF(BNQ!$D$9:$D1007,"🔴 Não feito")+COUNTIF(BNQ!$E$9:$E1007,"🔴 Não feito")>0,"🔴 Atenção",IF(COUNTIF(BNQ!$D$9:$D1007,"⚠️ Incompleto")+COUNTIF(BNQ!$E$9:$E1007,"⚠️ Incompleto")>0,"⚠️ Verificar","🟢 OK")) -> 🔴 Atenção
A16: Sistema Produtiva Júnior — SPJ | B16: =IFERROR(COUNTIF(SPJ!$D$9:$D1007,"✅ OK")/MAX(COUNTA(SPJ!$D$9:$D1007),1),0) -> 1 | C16: =IFERROR(COUNTIF(SPJ!$E$9:$E1007,"✅ OK")/MAX(COUNTA(SPJ!$E$9:$E1007),1),0) -> 0.81818182 | D16: =COUNTIF(SPJ!$K$9:$K1007,"✅ Aprovado") -> 0 | E16: =COUNTIF(SPJ!$K$9:$K1007,"✅ Aprovado") -> 0 | F16: =COUNTIF(SPJ!$K$9:$K1007,"✅ Aprovado") -> 0 | G16: =COUNTIF(SPJ!$D$9:$D1007,"🔴 Não feito")+COUNTIF(SPJ!$D$9:$D1007,"⚠️ Incompleto")+COUNTIF(SPJ!$E$9:$E1007,"🔴 Não feito")+COUNTIF(SPJ!$E$9:$E1007,"⚠️ Incompleto") -> 0 | H16: =IF(COUNTIF(SPJ!$D$9:$D1007,"🔴 Não feito")+COUNTIF(SPJ!$E$9:$E1007,"🔴 Não feito")>0,"🔴 Atenção",IF(COUNTIF(SPJ!$D$9:$D1007,"⚠️ Incompleto")+COUNTIF(SPJ!$E$9:$E1007,"⚠️ Incompleto")>0,"⚠️ Verificar","🟢 OK")) -> 🟢 OK
A17: Sistema Z2 — SZ2 | B17: =IFERROR(COUNTIF('EZ2'!$D$9:$D1007,"✅ OK")/MAX(COUNTA('EZ2'!$D$9:$D1007),1),0) -> 1 | C17: =IFERROR(COUNTIF('EZ2'!$E$9:$E1007,"✅ OK")/MAX(COUNTA('EZ2'!$E$9:$E1007),1),0) -> 1 | D17: =COUNTIF('EZ2'!$K$9:$K1007,"✅ Aprovado") -> 0 | E17: =COUNTIF('EZ2'!$K$9:$K1007,"🔄 Em teste") -> 0 | F17: =COUNTIF('EZ2'!$K$9:$K1007,"🔴 Reprovado") -> 0 | G17: =COUNTIF('EZ2'!$D$9:$D1007,"🔴 Não feito")+COUNTIF('EZ2'!$D$9:$D1007,"⚠️ Incompleto")+COUNTIF('EZ2'!$E$9:$E1007,"🔴 Não feito")+COUNTIF('EZ2'!$E$9:$E1007,"⚠️ Incompleto") -> 0 | H17: =IF(COUNTIF('EZ2'!$D$9:$D1007,"🔴 Não feito")+COUNTIF('EZ2'!$E$9:$E1007,"🔴 Não feito")>0,"🔴 Atenção",IF(COUNTIF('EZ2'!$D$9:$D1007,"⚠️ Incompleto")+COUNTIF('EZ2'!$E$9:$E1007,"⚠️ Incompleto")>0,"⚠️ Verificar","🟢 OK")) -> 🟢 OK
A18: Sistema AENTS — AENTS | B18: =IFERROR(COUNTIF(AENTS!$D$9:$D1007,"✅ OK")/MAX(COUNTA(AENTS!$D$9:$D1007),1),0) -> 1 | C18: =IFERROR(COUNTIF(AENTS!$E$9:$E1007,"✅ OK")/MAX(COUNTA(AENTS!$E$9:$E1007),1),0) -> 0 | D18: =COUNTIF(AENTS!$K$9:$K1007,"✅ Aprovado") -> 0 | E18: =COUNTIF(AENTS!$K$9:$K1007,"🔄 Em teste") -> 0 | F18: =COUNTIF(AENTS!$K$9:$K1007,"🔴 Reprovado") -> 0 | G18: =COUNTIF(AENTS!$D$9:$D1007,"🔴 Não feito")+COUNTIF(AENTS!$D$9:$D1007,"⚠️ Incompleto")+COUNTIF(AENTS!$E$9:$E1007,"🔴 Não feito")+COUNTIF(AENTS!$E$9:$E1007,"⚠️ Incompleto") -> 4 | H18: =IF(COUNTIF(AENTS!$D$9:$D1007,"🔴 Não feito")+COUNTIF(AENTS!$E$9:$E1007,"🔴 Não feito")>0,"🔴 Atenção",IF(COUNTIF(AENTS!$D$9:$D1007,"⚠️ Incompleto")+COUNTIF(AENTS!$E$9:$E1007,"⚠️ Incompleto")>0,"⚠️ Verificar","🟢 OK")) -> 🔴 Atenção
A19: Sistema Rotulare — Rotulare | B19: =IFERROR(COUNTIF(Rotulare!$D$9:$D1007,"✅ OK")/MAX(COUNTA(Rotulare!$D$9:$D1007),1),0) -> 0.85 | C19: =IFERROR(COUNTIF(Rotulare!$E$9:$E1007,"✅ OK")/MAX(COUNTA(Rotulare!$E$9:$E1007),1),0) -> 1 | D19: =COUNTIF(Rotulare!$K$9:$K1007,"✅ Aprovado") -> 0 | E19: =COUNTIF(Rotulare!$K$9:$K1007,"🔄 Em teste") -> 0 | F19: =COUNTIF(Rotulare!$K$9:$K1007,"🔴 Reprovado") -> 0 | G19: =COUNTIF(Rotulare!$D$9:$D1007,"🔴 Não feito")+COUNTIF(Rotulare!$D$9:$D1007,"⚠️ Incompleto")+COUNTIF(Rotulare!$E$9:$E1007,"🔴 Não feito")+COUNTIF(Rotulare!$E$9:$E1007,"⚠️ Incompleto") -> 3 | H19: =IF(COUNTIF(Rotulare!$D$9:$D1007,"🔴 Não feito")+COUNTIF(Rotulare!$E$9:$E1007,"🔴 Não feito")>0,"🔴 Atenção",IF(COUNTIF(Rotulare!$D$9:$D1007,"⚠️ Incompleto")+COUNTIF(Rotulare!$E$9:$E1007,"⚠️ Incompleto")>0,"⚠️ Verificar","🟢 OK")) -> 🔴 Atenção
A20: Sistema ODD — ODD | B20: =IFERROR(COUNTIF(ODD!$D$9:$D1007,"✅ OK")/MAX(COUNTA(ODD!$D$9:$D1007),1),0) -> 0 | C20: =IFERROR(COUNTIF(ODD!$E$9:$E1007,"✅ OK")/MAX(COUNTA(ODD!$E$9:$E1007),1),0) -> 0 | D20: =COUNTIF(ODD!$K$9:$K1007,"✅ Aprovado") -> 0 | E20: =COUNTIF(ODD!$K$9:$K1007,"🔄 Em teste") -> 0 | F20: =COUNTIF(ODD!$K$9:$K1007,"🔴 Reprovado") -> 0 | G20: =COUNTIF(ODD!$D$9:$D1007,"🔴 Não feito")+COUNTIF(ODD!$D$9:$D1007,"⚠️ Incompleto")+COUNTIF(ODD!$E$9:$E1007,"🔴 Não feito")+COUNTIF(ODD!$E$9:$E1007,"⚠️ Incompleto") -> 0 | H20: =IF(COUNTIF(ODD!$D$9:$D1007,"🔴 Não feito")+COUNTIF(ODD!$E$9:$E1007,"🔴 Não feito")>0,"🔴 Atenção",IF(COUNTIF(ODD!$D$9:$D1007,"⚠️ Incompleto")+COUNTIF(ODD!$E$9:$E1007,"⚠️ Incompleto")>0,"⚠️ Verificar","🟢 OK")) -> 🟢 OK
